odoo/addons/currency_old_rate_notify/README.rst
odoo/addons/currency_old_rate_notify/__init__.py
odoo/addons/currency_old_rate_notify/__manifest__.py
odoo/addons/currency_old_rate_notify/data/ir_config_parameter.xml
odoo/addons/currency_old_rate_notify/data/ir_cron.xml
odoo/addons/currency_old_rate_notify/i18n/currency_old_rate_notify.pot
odoo/addons/currency_old_rate_notify/i18n/es.po
odoo/addons/currency_old_rate_notify/i18n/fr.po
odoo/addons/currency_old_rate_notify/i18n/it.po
odoo/addons/currency_old_rate_notify/models/__init__.py
odoo/addons/currency_old_rate_notify/models/res_currency_rate.py
odoo/addons/currency_old_rate_notify/readme/CONFIGURE.rst
odoo/addons/currency_old_rate_notify/readme/CONTRIBUTORS.rst
odoo/addons/currency_old_rate_notify/readme/DESCRIPTION.rst
odoo/addons/currency_old_rate_notify/static/description/icon.png
odoo/addons/currency_old_rate_notify/static/description/index.html
odoo/addons/currency_old_rate_notify/static/description/notify_old_rates.png
odoo/addons/currency_old_rate_notify/tests/__init__.py
odoo/addons/currency_old_rate_notify/tests/test_old_rate_notify.py
odoo14_addon_currency_old_rate_notify-14.0.1.0.1.dev11.dist-info/METADATA
odoo14_addon_currency_old_rate_notify-14.0.1.0.1.dev11.dist-info/WHEEL
odoo14_addon_currency_old_rate_notify-14.0.1.0.1.dev11.dist-info/top_level.txt
odoo14_addon_currency_old_rate_notify-14.0.1.0.1.dev11.dist-info/RECORD
